{
  "main": {
    "id": "d0b749f8eeb8b9f9",
    "type": "split",
    "children": [
      {
        "id": "4bec06751d374f24",
        "type": "tabs",
        "dimension": 45.68345323741007,
        "children": [
          {
            "id": "f3c8c3353298fe9f",
            "type": "leaf",
            "state": {
              "type": "markdown",
              "state": {
                "file": "brainstorm/CONTEXT.md",
                "mode": "source",
                "source": false
              },
              "icon": "lucide-file",
              "title": "CONTEXT"
            }
          },
          {
            "id": "d5b73fe978a22596",
            "type": "leaf",
            "state": {
              "type": "markdown",
              "state": {
                "file": "brainstorm/books/ortuzar/@ortuzar2011modelling.md",
                "mode": "source",
                "source": false
              },
              "icon": "lucide-file",
              "title": "@ortuzar2011modelling"
            }
          },
          {
            "id": "48288529b7a3bb06",
            "type": "leaf",
            "state": {
              "type": "markdown",
              "state": {
                "file": "brainstorm/books/ortuzar/@ortuzar2011modelling.md",
                "mode": "source",
                "source": false
              },
              "icon": "lucide-file",
              "title": "@ortuzar2011modelling"
            }
          },
          {
            "id": "84cd0186c0f4be17",
            "type": "leaf",
            "state": {
              "type": "markdown",
              "state": {
                "file": "brainstorm/books/ortuzar/@ortuzar2011modelling.md",
                "mode": "source",
                "source": false
              },
              "icon": "lucide-file",
              "title": "@ortuzar2011modelling"
            }
          },
          {
            "id": "ea6890af58c47516",
            "type": "leaf",
            "state": {
              "type": "markdown",
              "state": {
                "file": "GEMINI.md",
                "mode": "source",
                "source": false
              },
              "icon": "lucide-file",
              "title": "GEMINI"
            }
          }
        ],
        "currentTab": 4
      },
      {
        "id": "54d113e5eeab9f1a",
        "type": "tabs",
        "dimension": 54.31654676258993,
        "children": [
          {
            "id": "30eeea041870662d",
            "type": "leaf",
            "state": {
              "type": "markdown",
              "state": {
                "file": "brainstorm/overview-bab-buku.md",
                "mode": "source",
                "source": false
              },
              "icon": "lucide-file",
              "title": "overview-bab-buku"
            }
          }
        ]
      }
    ],
    "direction": "vertical"
  },
  "left": {
    "id": "6ccb6c96337def0c",
    "type": "split",
    "children": [
      {
        "id": "3caee00400e7123b",
        "type": "tabs",
        "children": [
          {
            "id": "4cc82bc6504759d4",
            "type": "leaf",
            "state": {
              "type": "file-explorer",
              "state": {
                "sortOrder": "alphabetical",
                "autoReveal": false
              },
              "icon": "lucide-folder-closed",
              "title": "Files"
            }
          },
          {
            "id": "b66173e549812c1b",
            "type": "leaf",
            "state": {
              "type": "search",
              "state": {
                "query": "",
                "matchingCase": false,
                "explainSearch": false,
                "collapseAll": false,
                "extraContext": false,
                "sortOrder": "alphabetical"
              },
              "icon": "lucide-search",
              "title": "Search"
            }
          },
          {
            "id": "21eff1521679eae2",
            "type": "leaf",
            "state": {
              "type": "bookmarks",
              "state": {},
              "icon": "lucide-bookmark",
              "title": "Bookmarks"
            }
          }
        ]
      }
    ],
    "direction": "horizontal",
    "width": 300
  },
  "right": {
    "id": "3d59e0d44654b811",
    "type": "split",
    "children": [
      {
        "id": "4e6273c1ec90ff10",
        "type": "tabs",
        "children": [
          {
            "id": "9e70119d0fc38036",
            "type": "leaf",
            "state": {
              "type": "backlink",
              "state": {
                "collapseAll": false,
                "extraContext": false,
                "sortOrder": "alphabetical",
                "showSearch": false,
                "searchQuery": "",
                "backlinkCollapsed": false,
                "unlinkedCollapsed": true
              },
              "icon": "links-coming-in",
              "title": "Backlinks"
            }
          },
          {
            "id": "700348687a03ad3c",
            "type": "leaf",
            "state": {
              "type": "outgoing-link",
              "state": {
                "linksCollapsed": false,
                "unlinkedCollapsed": true
              },
              "icon": "links-going-out",
              "title": "Outgoing links"
            }
          },
          {
            "id": "6d8dd24bb0787a1e",
            "type": "leaf",
            "state": {
              "type": "tag",
              "state": {
                "sortOrder": "frequency",
                "useHierarchy": true,
                "showSearch": false,
                "searchQuery": ""
              },
              "icon": "lucide-tags",
              "title": "Tags"
            }
          },
          {
            "id": "efb66998ed818a2c",
            "type": "leaf",
            "state": {
              "type": "all-properties",
              "state": {
                "sortOrder": "frequency",
                "showSearch": false,
                "searchQuery": ""
              },
              "icon": "lucide-archive",
              "title": "All properties"
            }
          },
          {
            "id": "baa808ad55553022",
            "type": "leaf",
            "state": {
              "type": "outline",
              "state": {
                "file": "GEMINI.md",
                "followCursor": false,
                "showSearch": false,
                "searchQuery": ""
              },
              "icon": "lucide-list",
              "title": "Outline of GEMINI"
            }
          }
        ],
        "currentTab": 4
      }
    ],
    "direction": "horizontal",
    "width": 300,
    "collapsed": true
  },
  "left-ribbon": {
    "hiddenItems": {
      "switcher:Open quick switcher": false,
      "graph:Open graph view": false,
      "canvas:Create new canvas": false,
      "daily-notes:Open today's daily note": false,
      "templates:Insert template": false,
      "command-palette:Open command palette": false,
      "bases:Create new base": false
    }
  },
  "floating": {
    "id": "2382f104d13e26b8",
    "type": "floating",
    "children": [
      {
        "id": "da037ec99495ba46",
        "type": "window",
        "children": [
          {
            "id": "604bef8f4bf3f7e9",
            "type": "tabs",
            "children": [
              {
                "id": "1d3d94f4f068fc5e",
                "type": "leaf",
                "state": {
                  "type": "graph",
                  "state": {},
                  "icon": "lucide-git-fork",
                  "title": "Graph view"
                }
              }
            ]
          }
        ],
        "direction": "vertical",
        "x": 364,
        "y": 18,
        "width": 600,
        "height": 756,
        "maximize": false,
        "zoom": -1
      }
    ]
  },
  "active": "ea6890af58c47516",
  "lastOpenFiles": [
    "brainstorm/books/ortuzar/Bab 1 Introduction.md",
    "brainstorm/books/ortuzar/@ortuzar2011modelling.md",
    "brainstorm/books/ortuzar/Bab 3 Data and Space.md",
    "brainstorm/books/ortuzar/Bab 2 Mathematical Prerequisites.md",
    "brainstorm/books/rodrigue/Conclusion - Challenges for Transport Geography.md",
    "brainstorm/CONTEXT.md",
    "brainstorm/books/rodrigue/Bab 9 Transport Planning and Policy.md",
    "brainstorm/books/rodrigue/Bab 10 Methods in Transport Geography.md",
    "brainstorm/books/ortuzar",
    "brainstorm/output/20260618ar respon.md",
    "brainstorm/books/rodrigue/Bab 8 Urban Transportation.md",
    "brainstorm/books/rodrigue/Bab 7 Trades, Logistics, and Freight.md",
    "brainstorm/books/rodrigue/Bab 6 Transportation Terminals.md",
    "brainstorm/books/rodrigue/@rodrigue2020geography.md",
    "brainstorm/books/rodrigue/Bab 1 Transportation and Geography.md",
    "brainstorm/books/rodrigue/Bab 5 Transportation Mode.md",
    "brainstorm/books/rodrigue/Bab 4 Transport, Energy, and Environment.md",
    "brainstorm/books/rodrigue/Bab 3 Transportation, Economic, and Society.md",
    "brainstorm/books/rodrigue/Bab 2 Transportation and Spatial Structure.md",
    "brainstorm/rodrigue/@rodrigue2020geography.md",
    "brainstorm/books/rodrigue",
    "Bab 1 Transportasi dan Geografi.md",
    "brainstorm/books/Bab 1 Transportasi dan Geografi.md",
    "Untitled.md",
    "brainstorm/overview-bab-buku.md",
    "brainstorm/output/20260618a ternyata maks 10 hlm.md",
    "menulis/log/20260618-penyelesaian-masalah-render-quarto.md",
    "menulis/CONTEXT.md",
    "brainstorm/rodrigue/@rodrigue",
    "brainstorm/rodrigue",
    "brainstorm/research/Spatial Plan Evaluation Literature Review.md.crdownload",
    "brainstorm/research/Periodization and Evolution of Transportation Modeling in Indonesia.md.crdownload",
    "brainstorm/research",
    "menulis/log",
    "brainstorm/books/pdf/(Rose-Hulman CE380) Robert K Whitford, Jon D Fricker - Fundamentals of Transportation Engineering_ A Multimodal Systems Approach (2nd Edition)-The Scholar Collection (2018).pdf",
    "brainstorm/output/report_pdf.json",
    "brainstorm/assets/tamin-diagram.drawio.svg",
    "brainstorm/assets/Pasted image 20260612230823.png",
    "brainstorm/assets/manheim-diagram.svg"
  ]
}